{
  "main": {
    "id": "0d4987a3439055f4",
    "type": "split",
    "children": [
      {
        "id": "7326a89c39d8c04e",
        "type": "tabs",
        "children": [
          {
            "id": "83dd09a14fdad46a",
            "type": "leaf",
            "state": {
              "type": "markdown",
              "state": {
                "file": "PaperReading/PRF/Spartan --- Speculative avoidance of register allocations to transient values for performance and energy efficiency,.md",
                "mode": "source",
                "source": false
              }
            }
          },
          {
            "id": "13194c8983743908",
            "type": "leaf",
            "state": {
              "type": "markdown",
              "state": {
                "file": "PaperReading/Brief.md",
                "mode": "source",
                "source": false
              }
            }
          },
          {
            "id": "54e538e65ae48acb",
            "type": "leaf",
            "state": {
              "type": "markdown",
              "state": {
                "file": "PaperReading/PRF/Long Term Parking (LTP) --- Criticality-aware Resource Allocation in OOO Processors.md",
                "mode": "source",
                "source": false
              }
            }
          },
          {
            "id": "9f6ed19e26e10893",
            "type": "leaf",
            "state": {
              "type": "markdown",
              "state": {
                "file": "PaperReading/PRF/Checkpoint Processing and Recovery---Towards Scalable Large Instruction Window Processors.md",
                "mode": "source",
                "source": false
              }
            }
          },
          {
            "id": "ab105ae520e4abd7",
            "type": "leaf",
            "state": {
              "type": "markdown",
              "state": {
                "file": "PaperReading/Brief.md",
                "mode": "source",
                "source": false
              }
            }
          }
        ],
        "currentTab": 1
      }
    ],
    "direction": "vertical"
  },
  "left": {
    "id": "a419bb9042cec5b8",
    "type": "split",
    "children": [
      {
        "id": "daab66b2299a4343",
        "type": "tabs",
        "children": [
          {
            "id": "2fd97cb827b9533c",
            "type": "leaf",
            "state": {
              "type": "file-explorer",
              "state": {
                "sortOrder": "alphabetical"
              }
            }
          },
          {
            "id": "f31f343eec283533",
            "type": "leaf",
            "state": {
              "type": "search",
              "state": {
                "query": "",
                "matchingCase": false,
                "explainSearch": false,
                "collapseAll": false,
                "extraContext": false,
                "sortOrder": "alphabetical"
              }
            }
          },
          {
            "id": "29535ad4e0c271f4",
            "type": "leaf",
            "state": {
              "type": "starred",
              "state": {}
            }
          }
        ]
      }
    ],
    "direction": "horizontal",
    "width": 297.5
  },
  "right": {
    "id": "c67599e5a31e373f",
    "type": "split",
    "children": [
      {
        "id": "5bafa294df2cb63e",
        "type": "tabs",
        "children": [
          {
            "id": "6e3c28e033bd0213",
            "type": "leaf",
            "state": {
              "type": "backlink",
              "state": {
                "file": "PaperReading/Brief.md",
                "collapseAll": false,
                "extraContext": false,
                "sortOrder": "alphabetical",
                "showSearch": false,
                "searchQuery": "",
                "backlinkCollapsed": false,
                "unlinkedCollapsed": true
              }
            }
          },
          {
            "id": "98fac5d01a88fc24",
            "type": "leaf",
            "state": {
              "type": "outgoing-link",
              "state": {
                "file": "PaperReading/Brief.md",
                "linksCollapsed": false,
                "unlinkedCollapsed": true
              }
            }
          },
          {
            "id": "17bb7bbe29fbb5f5",
            "type": "leaf",
            "state": {
              "type": "tag",
              "state": {
                "sortOrder": "frequency",
                "useHierarchy": true
              }
            }
          },
          {
            "id": "5f78e536ee7ec726",
            "type": "leaf",
            "state": {
              "type": "outline",
              "state": {
                "file": "PaperReading/Brief.md"
              }
            }
          }
        ]
      }
    ],
    "direction": "horizontal",
    "width": 300,
    "collapsed": true
  },
  "left-ribbon": {
    "hiddenItems": {
      "switcher:Open quick switcher": false,
      "graph:Open graph view": false,
      "canvas:Create new canvas": false,
      "daily-notes:Open today's daily note": false,
      "templates:Insert template": false,
      "command-palette:Open command palette": false
    }
  },
  "active": "13194c8983743908",
  "lastOpenFiles": [
    "PaperReading/zlt/CRISP --- Critical Slice Prefetching.md",
    "PaperReading/PRF/Spartan --- Speculative avoidance of register allocations to transient values for performance and energy efficiency,.md",
    "PaperReading/zlt",
    "PaperReading/Brief.md",
    "PaperReading/OOO Commit/Out-of-Order Commit Processors.md",
    "Pasted image 20230417113815.png",
    "Pasted image 20230417113559.png",
    "Pasted image 20230417113114.png",
    "PaperReading/OOO Commit/img",
    "PaperReading/OOO Commit/img/Pasted image 20230417112931.png",
    "PaperReading/PRF/Checkpoint Processing and Recovery---Towards Scalable Large Instruction Window Processors.md",
    "PaperReading/OOO Commit",
    "PaperReading/Questions.md",
    "PaperReading/Eureka.md",
    "PaperReading/PRF/img/Pasted image 20230416195731.png",
    "PaperReading/PRF/Continual Flow Pipelines.md",
    "PaperReading/PRF/img/Pasted image 20230416201341.png",
    "PaperReading/PRF/img/Pasted image 20230416201302.png",
    "PaperReading/PRF/Long Term Parking (LTP) --- Criticality-aware Resource Allocation in OOO Processors.md",
    "PaperReading/PRF/img/Pasted image 20230416142424.png",
    "Templates/PaperReadingTemplate.md",
    "PaperReading/PRF/Increasing processor performance through early register release.md",
    "PaperReading/PRF/img/Pasted image 20230416150659.png",
    "PaperReading/PRF/img/Pasted image 20230416150453.png",
    "PaperReading/PRF/Speculative Register Reclamation.md",
    "PaperReading/PRF/Reducing the Complexity of the Register File in Dynamic Superscalar Processor.md",
    "PaperReading/PRF/A novel register renaming technique for out-of-order processors.md",
    "PaperReading/PRF/Virtual-Physical Registers.md",
    "PaperReading/PRF/Register Packing --- Exploiting Narrow-Width Operands for Reducing Register File Pressure.md",
    "PaperReading/FrontEnd/Register Traffic Analysis for Streamlining Inter-Operation Communicationin Fine-Grain ParaIIei Processors.md",
    "PaperReading/FrontEnd/Register renaming and dynamic speculation --- an alternative approach.md",
    "Commercial Tools/finesim/Usage.md",
    "PaperReading/PRF/Delaying Physical Register Allocation Through Virtual-Physical Registers.md",
    "PaperReading/PRF/Dynamic Register Renaming Through Virtual-Physical Registers.md",
    "PaperReading/PRF/Multiple-Banked Register File Architectures.md",
    "PaperReading/PRF/Banked Multiported Register Files for High-Frequency Superscalar Microprocessors.md",
    "PaperReading/PRF/Cherry---Checkpointed Early Resource Recycling in Out-of-order Microprocessors.md",
    "Programming Language/C++/Lamda表达式.md",
    "PaperReading/PRF/img",
    "PaperReading/FrontEnd/test1.md",
    "Templates",
    "PaperReading/IssueQueue",
    "Untitled.canvas",
    "PaperReading/PRF",
    "PaperReading",
    "Advanced Signal Processing/Completeness of Linear Space.pdf",
    "Programming Language/Markdown & LaTex/img"
  ]
}